arxiv_mcp/__init__.py
arxiv_mcp/app.py
arxiv_mcp/server.py
arxiv_mcp/utils.py
arxiv_mcp/prompts/__init__.py
arxiv_mcp/prompts/prompts.py
arxiv_mcp/resources/__init__.py
arxiv_mcp/resources/resources.py
arxiv_mcp/tools/__init__.py
arxiv_mcp/tools/tools.py
mseep_arxiv_paper_mcp-0.1.6.dist-info/licenses/LICENSE
mseep_arxiv_paper_mcp-0.1.6.dist-info/METADATA
mseep_arxiv_paper_mcp-0.1.6.dist-info/WHEEL
mseep_arxiv_paper_mcp-0.1.6.dist-info/entry_points.txt
mseep_arxiv_paper_mcp-0.1.6.dist-info/top_level.txt
mseep_arxiv_paper_mcp-0.1.6.dist-info/RECORD
